{
    "武汉": {
        "x": "114.305392",
        "y": "30.593098"
    },
    "孝感": {
        "x": "113.916902",
        "y": "30.924568"
    },
    "黄冈": {
        "x": "114.872316",
        "y": "30.453905"
    },
    "随州": {
        "x": "113.382458",
        "y": "31.690215"
    },
    "荆州": {
        "x": "112.239741",
        "y": "30.335165"
    },
    "襄阳": {
        "x": "112.122414",
        "y": "32.008986"
    },
    "黄石": {
        "x": "115.038520",
        "y": "30.199652"
    },
    "宜昌": {
        "x": "111.286471",
        "y": "30.691967"
    },
    "荆门": {
        "x": "112.199265",
        "y": "31.035423"
    },
    "咸宁": {
        "x": "114.322492",
        "y": "29.841443"
    },
    "鄂州": {
        "x": "114.894843",
        "y": "30.391940"
    },
    "十堰": {
        "x": "110.797990",
        "y": "32.629397"
    },
    "仙桃": {
        "x": "113.454593",
        "y": "30.362641"
    },
    "恩施州": {
        "x": "109.488172",
        "y": "30.272156"
    },
    "潜江": {
        "x": "112.900079",
        "y": "30.402109"
    },
    "神农架林区": {
        "x": "110.680448",
        "y": "31.743483"
    },
    "三亚": {
        "x": "109.511909",
        "y": "18.252847"
    },
    "天门": {
        "x": "113.175786",
        "y": "30.661214"
    },
    "海口": {
        "x": "110.198293",
        "y": "20.044001"
    },
    "万宁": {
        "x": "110.391073",
        "y": "18.795143"
    },
    "琼海": {
        "x": "110.474648",
        "y": "19.258341"
    },
    "陵水": {
        "x": "110.037503",
        "y": "18.506048"
    },
    "保亭": {
        "x": "109.702590",
        "y": "18.639130"
    },
    "琼中": {
        "x": "109.838389",
        "y": "19.033369"
    },
    "兰州": {
        "x": "103.834303",
        "y": "36.061089"
    },
    "文昌": {
        "x": "109.856655",
        "y": "19.493407"
    },
    "乐东": {
        "x": "109.173054",
        "y": "18.750259"
    },
    "天水": {
        "x": "105.724947",
        "y": "34.580863"
    },
    "定西": {
        "x": "104.626282",
        "y": "35.580662"
    },
    "陇南": {
        "x": "104.921841",
        "y": "33.400684"
    },
    "临夏": {
        "x": "103.210538",
        "y": "35.601182"
    },
    "甘南": {
        "x": "102.911027",
        "y": "34.983385"
    },
    "白银": {
        "x": "104.138559",
        "y": "36.544756"
    },
    "张掖": {
        "x": "100.449818",
        "y": "38.925875"
    },
    "庆阳": {
        "x": "107.643631",
        "y": "35.709077"
    },
    "金昌": {
        "x": "102.188043",
        "y": "38.520089"
    },
    "沈阳": {
        "x": "123.431474",
        "y": "41.805698"
    },
    "大连": {
        "x": "121.614682",
        "y": "38.914003"
    },
    "盘锦": {
        "x": "122.070714",
        "y": "41.119997"
    },
    "平凉": {
        "x": "106.665240",
        "y": "35.543051"
    },
    "锦州": {
        "x": "121.127003",
        "y": "41.095119"
    },
    "丹东": {
        "x": "124.354706",
        "y": "40.000499"
    },
    "葫芦岛": {
        "x": "120.836932",
        "y": "40.711052"
    },
    "本溪": {
        "x": "123.766485",
        "y": "41.294175"
    },
    "阜新": {
        "x": "121.670323",
        "y": "42.021619"
    },
    "铁岭": {
        "x": "123.726166",
        "y": "42.223769"
    },
    "朝阳": {
        "x": "120.471504",
        "y": "41.585133"
    },
    "辽阳": {
        "x": "123.236944",
        "y": "41.267244"
    },
    "营口": {
        "x": "122.235417",
        "y": "40.667012"
    },
    "鞍山": {
        "x": "122.994329",
        "y": "41.108647"
    },
    "运城": {
        "x": "111.007528",
        "y": "35.026412"
    },
    "晋中": {
        "x": "112.752694",
        "y": "37.687024"
    },
    "大同": {
        "x": "113.300129",
        "y": "40.076762"
    },
    "太原": {
        "x": "112.548879",
        "y": "37.870590"
    },
    "晋城": {
        "x": "112.851831",
        "y": "35.490701"
    },
    "朔州": {
        "x": "112.432825",
        "y": "39.331595"
    },
    "吕梁": {
        "x": "111.144319",
        "y": "37.518314"
    },
    "长治": {
        "x": "113.116255",
        "y": "36.195386"
    },
    "忻州": {
        "x": "112.734174",
        "y": "38.416663"
    },
    "阳泉": {
        "x": "113.580519",
        "y": "37.856971"
    },
    "临汾": {
        "x": "111.518976",
        "y": "36.088005"
    },
    "信阳": {
        "x": "114.091023",
        "y": "32.146983"
    },
    "郑州": {
        "x": "113.625368",
        "y": "34.746599"
    },
    "南阳": {
        "x": "112.528321",
        "y": "32.990833"
    },
    "驻马店": {
        "x": "114.022298",
        "y": "33.011529"
    },
    "商丘": {
        "x": "115.656370",
        "y": "34.414172"
    },
    "周口": {
        "x": "114.696951",
        "y": "33.626149"
    },
    "新乡": {
        "x": "113.926800",
        "y": "35.303004"
    },
    "安阳": {
        "x": "114.392392",
        "y": "36.097577"
    },
    "平顶山": {
        "x": "113.192661",
        "y": "33.766169"
    },
    "漯河": {
        "x": "114.016539",
        "y": "33.581412"
    },
    "许昌": {
        "x": "113.852640",
        "y": "34.035506"
    },
    "洛阳": {
        "x": "112.454040",
        "y": "34.619682"
    },
    "开封": {
        "x": "114.307581",
        "y": "34.797239"
    },
    "鹤壁": {
        "x": "114.297272",
        "y": "35.747225"
    },
    "焦作": {
        "x": "113.241823",
        "y": "35.215892"
    },
    "三门峡": {
        "x": "111.200135",
        "y": "34.772493"
    },
    "濮阳": {
        "x": "115.029215",
        "y": "35.761829"
    },
    "济源": {
        "x": "112.601918",
        "y": "35.067243"
    },
    "长沙": {
        "x": "112.938814",
        "y": "28.228209"
    },
    "岳阳": {
        "x": "113.128958",
        "y": "29.357104"
    },
    "常德": {
        "x": "111.698497",
        "y": "29.031673"
    },
    "邵阳": {
        "x": "111.467791",
        "y": "27.238892"
    },
    "娄底": {
        "x": "111.993497",
        "y": "27.700062"
    },
    "益阳": {
        "x": "112.355180",
        "y": "28.553860"
    },
    "衡阳": {
        "x": "112.571997",
        "y": "26.893230"
    },
    "怀化": {
        "x": "109.998488",
        "y": "27.554978"
    },
    "株洲": {
        "x": "113.134002",
        "y": "27.827550"
    },
    "永州": {
        "x": "111.613445",
        "y": "26.420394"
    },
    "郴州": {
        "x": "113.014717",
        "y": "25.770509"
    },
    "湘潭": {
        "x": "112.944049",
        "y": "27.829738"
    },
    "张家界": {
        "x": "110.479191",
        "y": "29.117096"
    },
    "杭州": {
        "x": "120.155070",
        "y": "30.274084"
    },
    "温州": {
        "x": "120.699366",
        "y": "27.994267"
    },
    "台州": {
        "x": "121.420757",
        "y": "28.656386"
    },
    "宁波": {
        "x": "121.550357",
        "y": "29.874556"
    },
    "金华": {
        "x": "119.647444",
        "y": "29.079059"
    },
    "绍兴": {
        "x": "120.580232",
        "y": "30.029752"
    },
    "衢州": {
        "x": "118.859457",
        "y": "28.970079"
    },
    "嘉兴": {
        "x": "120.755486",
        "y": "30.746129"
    },
    "丽水": {
        "x": "119.922796",
        "y": "28.467630"
    },
    "湖州": {
        "x": "120.086823",
        "y": "30.894348"
    },
    "舟山": {
        "x": "122.207215",
        "y": "29.985295"
    },
    "合肥": {
        "x": "117.227239",
        "y": "31.820586"
    },
    "阜阳": {
        "x": "115.814204",
        "y": "32.890124"
    },
    "安庆": {
        "x": "117.063754",
        "y": "30.543494"
    },
    "亳州": {
        "x": "115.778676",
        "y": "33.844582"
    },
    "六安": {
        "x": "116.521854",
        "y": "31.733699"
    },
    "蚌埠": {
        "x": "117.389719",
        "y": "32.916287"
    },
    "马鞍山": {
        "x": "118.506759",
        "y": "31.670452"
    },
    "宿州": {
        "x": "116.964356",
        "y": "33.646373"
    },
    "铜陵": {
        "x": "117.812079",
        "y": "30.945429"
    },
    "芜湖": {
        "x": "118.432941",
        "y": "31.352859"
    },
    "淮北": {
        "x": "116.798265",
        "y": "33.955844"
    },
    "淮南": {
        "x": "116.999932",
        "y": "32.625478"
    },
    "滁州": {
        "x": "118.317106",
        "y": "32.301556"
    },
    "池州": {
        "x": "117.491568",
        "y": "30.664800"
    },
    "宣城": {
        "x": "118.758816",
        "y": "30.940718"
    },
    "黄山": {
        "x": "118.337481",
        "y": "29.714655"
    },
    "深圳": {
        "x": "114.057868",
        "y": "22.543099"
    },
    "广州": {
        "x": "113.264434",
        "y": "23.129162"
    },
    "珠海": {
        "x": "113.576726",
        "y": "22.270715"
    },
    "东莞": {
        "x": "113.751765",
        "y": "23.020536"
    },
    "佛山": {
        "x": "113.121416",
        "y": "23.021548"
    },
    "中山": {
        "x": "113.392782",
        "y": "22.517645"
    },
    "惠州": {
        "x": "114.416196",
        "y": "23.111847"
    },
    "汕头": {
        "x": "116.681972",
        "y": "23.354091"
    },
    "湛江": {
        "x": "110.359377",
        "y": "21.270707"
    },
    "肇庆": {
        "x": "112.465091",
        "y": "23.047191"
    },
    "阳江": {
        "x": "111.982232",
        "y": "21.857958"
    },
    "梅州": {
        "x": "116.122238",
        "y": "24.288615"
    },
    "清远": {
        "x": "113.056031",
        "y": "23.681763"
    },
    "韶关": {
        "x": "113.597522",
        "y": "24.810403"
    },
    "江门": {
        "x": "113.081901",
        "y": "22.578738"
    },
    "揭阳": {
        "x": "116.372831",
        "y": "23.549993"
    },
    "茂名": {
        "x": "110.925456",
        "y": "21.662999"
    },
    "汕尾": {
        "x": "115.375278",
        "y": "22.786211"
    },
    "河源": {
        "x": "114.700447",
        "y": "23.743538"
    },
    "潮州": {
        "x": "116.622603",
        "y": "23.656950"
    },
    "苏州": {
        "x": "120.585315",
        "y": "31.298886"
    },
    "徐州": {
        "x": "117.284124",
        "y": "34.205768"
    },
    "无锡": {
        "x": "120.311910",
        "y": "31.491169"
    },
    "南京": {
        "x": "118.796877",
        "y": "32.060255"
    },
    "泰州": {
        "x": "119.923116",
        "y": "32.455778"
    },
    "淮安": {
        "x": "119.015285",
        "y": "33.610353"
    },
    "南通": {
        "x": "120.894291",
        "y": "31.980171"
    },
    "连云港": {
        "x": "119.221611",
        "y": "34.596653"
    },
    "常州": {
        "x": "119.973987",
        "y": "31.810689"
    },
    "扬州": {
        "x": "119.412966",
        "y": "32.394210"
    },
    "盐城": {
        "x": "120.163561",
        "y": "33.347382"
    },
    "镇江": {
        "x": "119.425836",
        "y": "32.187849"
    },
    "宿迁": {
        "x": "118.275198",
        "y": "33.963232"
    },
    "贵阳": {
        "x": "106.630153",
        "y": "26.647661"
    },
    "毕节": {
        "x": "105.283992",
        "y": "27.302589"
    },
    "六盘水": {
        "x": "104.830359",
        "y": "26.592666"
    },
    "遵义": {
        "x": "106.927389",
        "y": "27.725654"
    },
    "铜仁": {
        "x": "109.189598",
        "y": "27.731514"
    },
    "黔南州": {
        "x": "107.522097",
        "y": "26.254092"
    },
    "黔东南州": {
        "x": "107.982859",
        "y": "26.583442"
    },
    "黔西南州": {
        "x": "104.906396",
        "y": "25.087825"
    },
    "安顺": {
        "x": "105.947593",
        "y": "26.253072"
    },
    "莆田": {
        "x": "119.007777",
        "y": "25.454084"
    },
    "福州": {
        "x": "119.296494",
        "y": "26.074507"
    },
    "泉州": {
        "x": "118.675675",
        "y": "24.874132"
    },
    "厦门": {
        "x": "118.089425",
        "y": "24.479833"
    },
    "漳州": {
        "x": "117.647481",
        "y": "24.512948"
    },
    "宁德": {
        "x": "119.547932",
        "y": "26.665617"
    },
    "南平": {
        "x": "118.177708",
        "y": "26.641768"
    },
    "三明": {
        "x": "117.638678",
        "y": "26.263406"
    },
    "龙岩": {
        "x": "117.017536",
        "y": "25.075123"
    },
    "哈尔滨": {
        "x": "126.534967",
        "y": "45.803775"
    },
    "绥化": {
        "x": "126.968887",
        "y": "46.653845"
    },
    "齐齐哈尔": {
        "x": "123.918186",
        "y": "47.354348"
    },
    "双鸭山": {
        "x": "131.159133",
        "y": "46.646508"
    },
    "鸡西": {
        "x": "130.969333",
        "y": "45.295075"
    },
    "佳木斯": {
        "x": "130.318917",
        "y": "46.799922"
    },
    "大庆": {
        "x": "125.103784",
        "y": "46.589309"
    },
    "牡丹江": {
        "x": "129.633168",
        "y": "44.551653"
    },
    "七台河": {
        "x": "131.003138",
        "y": "45.771726"
    },
    "鹤岗": {
        "x": "130.297964",
        "y": "47.349916"
    },
    "大兴安岭": {
        "x": "124.711080",
        "y": "52.335206"
    },
    "黑河": {
        "x": "127.528560",
        "y": "50.245329"
    },
    "北海": {
        "x": "109.119927",
        "y": "21.481254"
    },
    "南宁": {
        "x": "108.366543",
        "y": "22.817002"
    },
    "桂林": {
        "x": "110.290194",
        "y": "25.273566"
    },
    "柳州": {
        "x": "109.415953",
        "y": "24.325502"
    },
    "防城港": {
        "x": "108.353846",
        "y": "21.686860"
    },
    "梧州": {
        "x": "111.279115",
        "y": "23.476962"
    },
    "玉林": {
        "x": "110.164756",
        "y": "22.636379"
    },
    "河池": {
        "x": "108.085261",
        "y": "24.692931"
    },
    "贵港": {
        "x": "109.598926",
        "y": "23.111530"
    },
    "贺州": {
        "x": "111.566694",
        "y": "24.403582"
    },
    "钦州": {
        "x": "108.654146",
        "y": "21.979933"
    },
    "石家庄": {
        "x": "114.514859",
        "y": "38.042306"
    },
    "沧州": {
        "x": "116.838834",
        "y": "38.304477"
    },
    "百色": {
        "x": "106.618201",
        "y": "23.902333"
    },
    "保定": {
        "x": "115.464806",
        "y": "38.873891"
    },
    "邢台": {
        "x": "114.504844",
        "y": "37.070589"
    },
    "邯郸": {
        "x": "114.538961",
        "y": "36.625657"
    },
    "廊坊": {
        "x": "116.683752",
        "y": "39.538047"
    },
    "张家口": {
        "x": "114.887543",
        "y": "40.824418"
    },
    "唐山": {
        "x": "118.180193",
        "y": "39.630867"
    },
    "衡水": {
        "x": "115.670177",
        "y": "37.738920"
    },
    "承德": {
        "x": "117.962410",
        "y": "40.954071"
    },
    "秦皇岛": {
        "x": "119.600492",
        "y": "39.935385"
    },
    "吉林市": {
        "x": "126.549572",
        "y": "43.837883"
    },
    "长春": {
        "x": "125.323544",
        "y": "43.817071"
    },
    "四平": {
        "x": "124.350398",
        "y": "43.166419"
    },
    "延边": {
        "x": "129.508946",
        "y": "42.891253"
    },
    "公主岭": {
        "x": "124.829026",
        "y": "43.503352"
    },
    "辽源": {
        "x": "125.143532",
        "y": "42.887918"
    },
    "松原": {
        "x": "124.825117",
        "y": "45.141789"
    },
    "通化": {
        "x": "125.939697",
        "y": "41.728401"
    },
    "临沂": {
        "x": "118.356448",
        "y": "35.104672"
    },
    "青岛": {
        "x": "120.382639",
        "y": "36.067082"
    },
    "济南": {
        "x": "117.119999",
        "y": "36.651216"
    },
    "烟台": {
        "x": "121.447935",
        "y": "37.463822"
    },
    "威海": {
        "x": "122.120419",
        "y": "37.513068"
    },
    "济宁": {
        "x": "116.587098",
        "y": "35.414921"
    },
    "德州": {
        "x": "116.357464",
        "y": "37.434092"
    },
    "枣庄": {
        "x": "117.323725",
        "y": "34.810487"
    },
    "潍坊": {
        "x": "119.161755",
        "y": "36.706774"
    },
    "日照": {
        "x": "119.526888",
        "y": "35.416377"
    },
    "菏泽": {
        "x": "115.480656",
        "y": "35.233750"
    },
    "泰安": {
        "x": "117.087614",
        "y": "36.200252"
    },
    "淄博": {
        "x": "118.054927",
        "y": "36.813487"
    },
    "聊城": {
        "x": "115.985371",
        "y": "36.456703"
    },
    "滨州": {
        "x": "117.970703",
        "y": "37.381990"
    },
    "成都": {
        "x": "104.066541",
        "y": "30.572269"
    },
    "南充": {
        "x": "106.110698",
        "y": "30.837793"
    },
    "达州": {
        "x": "107.468023",
        "y": "31.209571"
    },
    "广安": {
        "x": "106.633212",
        "y": "30.455961"
    },
    "绵阳": {
        "x": "104.679114",
        "y": "31.467450"
    },
    "巴中": {
        "x": "106.747477",
        "y": "31.867903"
    },
    "内江": {
        "x": "105.058433",
        "y": "29.580228"
    },
    "德阳": {
        "x": "104.397894",
        "y": "31.126855"
    },
    "泸州": {
        "x": "105.442258",
        "y": "28.871810"
    },
    "攀枝花": {
        "x": "101.718637",
        "y": "26.582347"
    },
    "甘孜州": {
        "x": "101.962310",
        "y": "30.049520"
    },
    "自贡": {
        "x": "104.778442",
        "y": "29.339030"
    },
    "宜宾": {
        "x": "104.643215",
        "y": "28.751768"
    },
    "凉山州": {
        "x": "102.267335",
        "y": "27.881610"
    },
    "雅安": {
        "x": "103.013261",
        "y": "29.980537"
    },
    "广元": {
        "x": "105.843357",
        "y": "32.435435"
    },
    "遂宁": {
        "x": "105.592898",
        "y": "30.532847"
    },
    "眉山": {
        "x": "103.848538",
        "y": "30.075439"
    },
    "乐山": {
        "x": "103.765568",
        "y": "29.552106"
    },
    "资阳": {
        "x": "104.627636",
        "y": "30.128901"
    },
    "万州区": {
        "x": "108.408661",
        "y": "30.807667"
    },
    "九龙坡区": {
        "x": "106.531920",
        "y": "29.514190"
    },
    "阿坝州": {
        "x": "102.224653",
        "y": "31.899413"
    },
    "开州区": {
        "x": "108.393135",
        "y": "31.160711"
    },
    "云阳县": {
        "x": "108.697324",
        "y": "30.930613"
    },
    "江北区": {
        "x": "106.574271",
        "y": "29.606703"
    },
    "渝中区": {
        "x": "106.568892",
        "y": "29.552750"
    },
    "垫江县": {
        "x": "107.333390",
        "y": "30.327717"
    },
    "两江新区": {
        "x": "128.113571",
        "y": "42.654331"
    },
    "渝北区": {
        "x": "106.631187",
        "y": "29.718143"
    },
    "忠县": {
        "x": "108.039002",
        "y": "30.299560"
    },
    "石柱县": {
        "x": "108.112941",
        "y": "29.996400"
    },
    "长寿区": {
        "x": "107.081283",
        "y": "29.857996"
    },
    "綦江区": {
        "x": "106.651362",
        "y": "29.028067"
    },
    "巫溪县": {
        "x": "109.570062",
        "y": "31.398604"
    },
    "合川区": {
        "x": "106.276130",
        "y": "29.972084"
    },
    "奉节县": {
        "x": "109.463987",
        "y": "31.018498"
    },
    "璧山区": {
        "x": "106.227305",
        "y": "29.592024"
    },
    "巫山县": {
        "x": "109.879153",
        "y": "31.074834"
    },
    "南岸区": {
        "x": "106.644428",
        "y": "29.500297"
    },
    "荣昌区": {
        "x": "105.594623",
        "y": "29.405002"
    },
    "大渡口区": {
        "x": "106.482347",
        "y": "29.484527"
    },
    "大足区": {
        "x": "105.721733",
        "y": "29.707032"
    },
    "铜梁区": {
        "x": "106.056404",
        "y": "29.844811"
    },
    "丰都县": {
        "x": "107.730895",
        "y": "29.863500"
    },
    "潼南区": {
        "x": "105.840556",
        "y": "30.191013"
    },
    "江津区": {
        "x": "106.259281",
        "y": "29.290069"
    },
    "高新区": {
        "x": "119.929878",
        "y": "31.643923"
    },
    "巴南区": {
        "x": "106.533840",
        "y": "29.375528"
    },
    "永川区": {
        "x": "105.927376",
        "y": "29.356117"
    },
    "梁平区": {
        "x": "107.800034",
        "y": "30.672167"
    },
    "城口县": {
        "x": "108.664214",
        "y": "31.947633"
    },
    "涪陵区": {
        "x": "107.389298",
        "y": "29.703113"
    },
    "黔江区": {
        "x": "108.770678",
        "y": "29.533610"
    },
    "沙坪坝区": {
        "x": "106.456878",
        "y": "29.541145"
    },
    "秀山县": {
        "x": "109.009994",
        "y": "28.409341"
    },
    "武隆区": {
        "x": "107.756546",
        "y": "29.323761"
    },
    "包头": {
        "x": "109.840347",
        "y": "40.657449"
    },
    "鄂尔多斯": {
        "x": "109.781327",
        "y": "39.608266"
    },
    "呼和浩特": {
        "x": "111.749180",
        "y": "40.842585"
    },
    "巴彦淖尔": {
        "x": "107.387657",
        "y": "40.743213"
    },
    "乌兰察布": {
        "x": "113.132585",
        "y": "40.994785"
    },
    "呼伦贝尔": {
        "x": "119.765744",
        "y": "49.211574"
    },
    "锡林郭勒盟": {
        "x": "116.048222",
        "y": "43.933454"
    },
    "乌海市": {
        "x": "106.794249",
        "y": "39.655388"
    },
    "赤峰": {
        "x": "118.886856",
        "y": "42.257817"
    },
    "兴安盟": {
        "x": "122.067042",
        "y": "46.077561"
    },
    "通辽": {
        "x": "122.243444",
        "y": "43.652890"
    },
    "西安": {
        "x": "108.940174",
        "y": "34.341568"
    },
    "安康": {
        "x": "109.029022",
        "y": "32.684714"
    },
    "咸阳": {
        "x": "108.708991",
        "y": "34.329605"
    },
    "汉中": {
        "x": "107.023323",
        "y": "33.067480"
    },
    "宝鸡": {
        "x": "107.237974",
        "y": "34.361979"
    },
    "渭南": {
        "x": "109.509786",
        "y": "34.499995"
    },
    "延安": {
        "x": "109.489727",
        "y": "36.585455"
    },
    "铜川": {
        "x": "108.945233",
        "y": "34.896756"
    },
    "商洛": {
        "x": "109.940477",
        "y": "33.870422"
    },
    "榆林": {
        "x": "109.734589",
        "y": "38.285390"
    },
    "韩城": {
        "x": "110.442847",
        "y": "35.476788"
    },
    "昆明": {
        "x": "102.832891",
        "y": "24.880095"
    },
    "西双版纳": {
        "x": "100.797777",
        "y": "22.007351"
    },
    "玉溪": {
        "x": "102.546543",
        "y": "24.352036"
    },
    "昭通": {
        "x": "103.717465",
        "y": "27.338257"
    },
    "曲靖": {
        "x": "103.796167",
        "y": "25.489999"
    },
    "保山": {
        "x": "99.161761",
        "y": "25.112046"
    },
    "丽江": {
        "x": "100.227750",
        "y": "26.855047"
    },
    "大理": {
        "x": "100.267638",
        "y": "25.606486"
    },
    "德宏": {
        "x": "98.584895",
        "y": "24.433353"
    },
    "普洱": {
        "x": "100.966512",
        "y": "22.825065"
    },
    "楚雄": {
        "x": "101.528068",
        "y": "25.045532"
    },
    "临沧": {
        "x": "100.079583",
        "y": "23.877573"
    },
    "浦东新区": {
        "x": "121.544379",
        "y": "31.221517"
    },
    "静安区": {
        "x": "121.459384",
        "y": "31.247105"
    },
    "徐汇区": {
        "x": "121.437866",
        "y": "31.199190"
    },
    "宝山区": {
        "x": "121.489612",
        "y": "31.405457"
    },
    "闵行区": {
        "x": "121.381709",
        "y": "31.112813"
    },
    "松江区": {
        "x": "121.227747",
        "y": "31.032243"
    },
    "长宁区": {
        "x": "121.424624",
        "y": "31.220367"
    },
    "虹口区": {
        "x": "121.505133",
        "y": "31.264600"
    },
    "奉贤区": {
        "x": "121.474042",
        "y": "30.917795"
    },
    "普陀区": {
        "x": "122.323867",
        "y": "29.971760"
    },
    "杨浦区": {
        "x": "121.526077",
        "y": "31.259541"
    },
    "黄浦区": {
        "x": "121.469240",
        "y": "31.229860"
    },
    "嘉定区": {
        "x": "121.265300",
        "y": "31.375602"
    },
    "青浦区": {
        "x": "121.124178",
        "y": "31.150681"
    },
    "金山区": {
        "x": "121.341970",
        "y": "30.741991"
    },
    "崇明区": {
        "x": "121.397514",
        "y": "31.626945"
    },
    "海淀区": {
        "x": "116.329519",
        "y": "39.972134"
    },
    "朝阳区": {
        "x": "125.288319",
        "y": "43.833513"
    },
    "大兴区": {
        "x": "116.341014",
        "y": "39.784747"
    },
    "西城区": {
        "x": "116.365868",
        "y": "39.912289"
    },
    "丰台区": {
        "x": "116.287149",
        "y": "39.858427"
    },
    "昌平区": {
        "x": "116.231204",
        "y": "40.220660"
    },
    "房山区": {
        "x": "116.143267",
        "y": "39.749144"
    },
    "通州区": {
        "x": "121.075087",
        "y": "32.064161"
    },
    "石景山区": {
        "x": "116.222982",
        "y": "39.906611"
    },
    "东城区": {
        "x": "116.416357",
        "y": "39.928353"
    },
    "顺义区": {
        "x": "116.654561",
        "y": "40.130347"
    },
    "怀柔区": {
        "x": "116.642349",
        "y": "40.315704"
    },
    "门头沟区": {
        "x": "116.102009",
        "y": "39.940646"
    },
    "延庆区": {
        "x": "115.974848",
        "y": "40.456951"
    },
    "宝坻区": {
        "x": "117.309863",
        "y": "39.717379"
    },
    "河北区": {
        "x": "117.196648",
        "y": "39.147869"
    },
    "河东区": {
        "x": "118.402893",
        "y": "35.089917"
    },
    "和平区": {
        "x": "123.395680",
        "y": "41.789450"
    },
    "河西区": {
        "x": "117.223372",
        "y": "39.109563"
    },
    "宁河区": {
        "x": "117.826625",
        "y": "39.329858"
    },
    "东丽区": {
        "x": "117.314324",
        "y": "39.086569"
    },
    "南开区": {
        "x": "117.150738",
        "y": "39.138203"
    },
    "西青区": {
        "x": "117.013949",
        "y": "39.141591"
    },
    "滨海新区": {
        "x": "117.780670",
        "y": "39.246083"
    },
    "红桥区": {
        "x": "117.151533",
        "y": "39.167345"
    },
    "津南区": {
        "x": "117.391976",
        "y": "38.984526"
    },
    "海北州": {
        "x": "100.900997",
        "y": "36.954413"
    },
    "乌鲁木齐": {
        "x": "87.616848",
        "y": "43.825592"
    },
    "西宁": {
        "x": "101.778228",
        "y": "36.617144"
    },
    "伊犁州": {
        "x": "81.324136",
        "y": "43.916823"
    },
    "吐鲁番": {
        "x": "89.189655",
        "y": "42.951384"
    },
    "阿克苏": {
        "x": "80.260605",
        "y": "41.168779"
    },
    "九江": {
        "x": "116.001930",
        "y": "29.705077"
    },
    "新余": {
        "x": "114.917346",
        "y": "27.817808"
    },
    "南昌": {
        "x": "115.858197",
        "y": "28.682892"
    },
    "上饶": {
        "x": "117.943433",
        "y": "28.454862"
    },
    "宜春": {
        "x": "114.416778",
        "y": "27.815619"
    },
    "赣州": {
        "x": "114.935029",
        "y": "25.831829"
    },
    "抚州": {
        "x": "116.358181",
        "y": "27.949217"
    },
    "吉安": {
        "x": "114.992509",
        "y": "27.113443"
    },
    "萍乡": {
        "x": "113.854556",
        "y": "27.622768"
    },
    "景德镇": {
        "x": "117.178419",
        "y": "29.268835"
    },
    "鹰潭": {
        "x": "117.069202",
        "y": "28.260189"
    },
    "拉萨": {
        "x": "91.140856",
        "y": "29.645554"
    },
    "中卫": {
        "x": "105.196902",
        "y": "37.499972"
    },
    "银川": {
        "x": "106.230909",
        "y": "38.487193"
    },
    "固原": {
        "x": "106.242610",
        "y": "36.015855"
    },
    "吴忠": {
        "x": "106.198393",
        "y": "37.997460"
    },
    "宁东管委会": {
        "x": "106.586197",
        "y": "38.164406"
    },
    "石嘴山": {
        "x": "106.383303",
        "y": "38.983236"
    },
    "儋州": {
        "x": "109.580811",
        "y": "19.521134"
    },
    "临高": {
        "x": "110.43782",
        "y": "19.99866"
    },
    "昌江": {
        "x": "117.20136",
        "y": "29.29557"
    },
    "定安": {
        "x": "110.35900",
        "y": "19.68130"
    },
    "澄迈": {
        "x": "110.00700",
        "y": "19.73840"
    },
    "湘西自治州": {
        "x": "109.68962",
        "y": "28.25739"
    },
    "彭水县": {
        "x": "108.16352",
        "y": "29.28818"
    },
    "酉阳县": {
        "x": "108.76586",
        "y": "28.85398"
    },
    "杨凌": {
        "x": "108.09482",
        "y": "34.26636"
    },
    "红河": {
        "x": "103.37500",
        "y": "23.36430"
    },
    "文山": {
        "x": "104.21600",
        "y": "23.37422"
    },
    "外地来沪人员": {
        "x": "121.47353",
        "y": "31.23045"
    },
    "未知地区": {
        "x": "114.13948",
        "y": "30.47811"
    },
    "外地来京人员": {
        "x": "116.36511",
        "y": "39.98832"
    },
    "待明确地区": {
        "x": "114.13948",
        "y": "30.47811"
    },
    "外地来津人员": {
        "x": "117.20300",
        "y": "39.08780"
    },
    "第九师": {
        "x": "114.13948",
        "y": "30.47811"
    },
    "昌吉": {
        "x": "87.30840",
        "y": "44.01110"
    },
    "第七师": {
        "x": "114.13948",
        "y": "30.47811"
    },
    "第八师": {
        "x": "114.13948",
        "y": "30.47811"
    },
    "第六师": {
        "x": "114.13948",
        "y": "30.47811"
    }
}